{"dependencies":[{"name":"C:\\Users\\qison\\Google Drive\\tfjs_vae\\nodejs_version\\package.json","includedInParent":true,"mtime":1528206326997},{"name":"C:\\Users\\qison\\Google Drive\\tfjs_vae\\nodejs_version\\.babelrc","includedInParent":true,"mtime":1528197961732},{"name":"C:\\Users\\qison\\Google Drive\\tfjs_vae\\nodejs_version\\node_modules\\is-plain-obj\\package.json","includedInParent":true,"mtime":1446715911000}],"generated":{"js":"'use strict';\nvar toString = Object.prototype.toString;\n\nmodule.exports = function (x) {\n\tvar prototype;\n\treturn toString.call(x) === '[object Object]' && (prototype = Object.getPrototypeOf(x), prototype === null || prototype === Object.getPrototypeOf({}));\n};\n","map":{"mappings":[{"source":"node_modules\\is-plain-obj\\index.js","original":{"line":1,"column":0},"generated":{"line":1,"column":0}},{"source":"node_modules\\is-plain-obj\\index.js","original":{"line":2,"column":0},"generated":{"line":2,"column":0}},{"source":"node_modules\\is-plain-obj\\index.js","original":{"line":3,"column":0},"generated":{"line":3,"column":0}},{"source":"node_modules\\is-plain-obj\\index.js","original":{"line":4,"column":0},"generated":{"line":4,"column":0}},{"source":"node_modules\\is-plain-obj\\index.js","original":{"line":5,"column":0},"generated":{"line":5,"column":0}},{"source":"node_modules\\is-plain-obj\\index.js","original":{"line":6,"column":0},"generated":{"line":6,"column":0}},{"source":"node_modules\\is-plain-obj\\index.js","original":{"line":7,"column":0},"generated":{"line":7,"column":0}},{"source":"node_modules\\is-plain-obj\\index.js","original":{"line":8,"column":0},"generated":{"line":8,"column":0}}],"sources":{"node_modules\\is-plain-obj\\index.js":"'use strict';\nvar toString = Object.prototype.toString;\n\nmodule.exports = function (x) {\n\tvar prototype;\n\treturn toString.call(x) === '[object Object]' && (prototype = Object.getPrototypeOf(x), prototype === null || prototype === Object.getPrototypeOf({}));\n};\n"},"lineCount":8}},"hash":"7c59c61e17ec5fbe5c4d94c6d0a7d236","cacheData":{"env":{}}}