{"dependencies":[{"name":"C:\\Users\\qison\\package.json","includedInParent":true,"mtime":1526331035212},{"name":"C:\\Users\\qison\\Google Drive\\tfjs_vae\\nodejs_version\\node_modules\\a-big-triangle\\package.json","includedInParent":true,"mtime":1481071762000},{"name":"weak-map","loc":{"line":3,"column":60}},{"name":"gl-buffer","loc":{"line":4,"column":27}},{"name":"gl-vao","loc":{"line":5,"column":27}}],"generated":{"js":"'use strict'\n\nvar weakMap      = typeof WeakMap === 'undefined' ? require('weak-map') : WeakMap\nvar createBuffer = require('gl-buffer')\nvar createVAO    = require('gl-vao')\n\nvar TriangleCache = new weakMap()\n\nfunction createABigTriangle(gl) {\n\n  var triangleVAO = TriangleCache.get(gl)\n  var handle = triangleVAO && (triangleVAO._triangleBuffer.handle || triangleVAO._triangleBuffer.buffer)\n  if(!handle || !gl.isBuffer(handle)) {\n    var buf = createBuffer(gl, new Float32Array([-1, -1, -1, 4, 4, -1]))\n    triangleVAO = createVAO(gl, [\n      { buffer: buf,\n        type: gl.FLOAT,\n        size: 2\n      }\n    ])\n    triangleVAO._triangleBuffer = buf\n    TriangleCache.set(gl, triangleVAO)\n  }\n  triangleVAO.bind()\n  gl.drawArrays(gl.TRIANGLES, 0, 3)\n  triangleVAO.unbind()\n}\n\nmodule.exports = createABigTriangle\n","map":{"mappings":[{"source":"nodejs_version\\node_modules\\a-big-triangle\\triangle.js","original":{"line":1,"column":0},"generated":{"line":1,"column":0}},{"source":"nodejs_version\\node_modules\\a-big-triangle\\triangle.js","original":{"line":2,"column":0},"generated":{"line":2,"column":0}},{"source":"nodejs_version\\node_modules\\a-big-triangle\\triangle.js","original":{"line":3,"column":0},"generated":{"line":3,"column":0}},{"source":"nodejs_version\\node_modules\\a-big-triangle\\triangle.js","original":{"line":4,"column":0},"generated":{"line":4,"column":0}},{"source":"nodejs_version\\node_modules\\a-big-triangle\\triangle.js","original":{"line":5,"column":0},"generated":{"line":5,"column":0}},{"source":"nodejs_version\\node_modules\\a-big-triangle\\triangle.js","original":{"line":6,"column":0},"generated":{"line":6,"column":0}},{"source":"nodejs_version\\node_modules\\a-big-triangle\\triangle.js","original":{"line":7,"column":0},"generated":{"line":7,"column":0}},{"source":"nodejs_version\\node_modules\\a-big-triangle\\triangle.js","original":{"line":8,"column":0},"generated":{"line":8,"column":0}},{"source":"nodejs_version\\node_modules\\a-big-triangle\\triangle.js","original":{"line":9,"column":0},"generated":{"line":9,"column":0}},{"source":"nodejs_version\\node_modules\\a-big-triangle\\triangle.js","original":{"line":10,"column":0},"generated":{"line":10,"column":0}},{"source":"nodejs_version\\node_modules\\a-big-triangle\\triangle.js","original":{"line":11,"column":0},"generated":{"line":11,"column":0}},{"source":"nodejs_version\\node_modules\\a-big-triangle\\triangle.js","original":{"line":12,"column":0},"generated":{"line":12,"column":0}},{"source":"nodejs_version\\node_modules\\a-big-triangle\\triangle.js","original":{"line":13,"column":0},"generated":{"line":13,"column":0}},{"source":"nodejs_version\\node_modules\\a-big-triangle\\triangle.js","original":{"line":14,"column":0},"generated":{"line":14,"column":0}},{"source":"nodejs_version\\node_modules\\a-big-triangle\\triangle.js","original":{"line":15,"column":0},"generated":{"line":15,"column":0}},{"source":"nodejs_version\\node_modules\\a-big-triangle\\triangle.js","original":{"line":16,"column":0},"generated":{"line":16,"column":0}},{"source":"nodejs_version\\node_modules\\a-big-triangle\\triangle.js","original":{"line":17,"column":0},"generated":{"line":17,"column":0}},{"source":"nodejs_version\\node_modules\\a-big-triangle\\triangle.js","original":{"line":18,"column":0},"generated":{"line":18,"column":0}},{"source":"nodejs_version\\node_modules\\a-big-triangle\\triangle.js","original":{"line":19,"column":0},"generated":{"line":19,"column":0}},{"source":"nodejs_version\\node_modules\\a-big-triangle\\triangle.js","original":{"line":20,"column":0},"generated":{"line":20,"column":0}},{"source":"nodejs_version\\node_modules\\a-big-triangle\\triangle.js","original":{"line":21,"column":0},"generated":{"line":21,"column":0}},{"source":"nodejs_version\\node_modules\\a-big-triangle\\triangle.js","original":{"line":22,"column":0},"generated":{"line":22,"column":0}},{"source":"nodejs_version\\node_modules\\a-big-triangle\\triangle.js","original":{"line":23,"column":0},"generated":{"line":23,"column":0}},{"source":"nodejs_version\\node_modules\\a-big-triangle\\triangle.js","original":{"line":24,"column":0},"generated":{"line":24,"column":0}},{"source":"nodejs_version\\node_modules\\a-big-triangle\\triangle.js","original":{"line":25,"column":0},"generated":{"line":25,"column":0}},{"source":"nodejs_version\\node_modules\\a-big-triangle\\triangle.js","original":{"line":26,"column":0},"generated":{"line":26,"column":0}},{"source":"nodejs_version\\node_modules\\a-big-triangle\\triangle.js","original":{"line":27,"column":0},"generated":{"line":27,"column":0}},{"source":"nodejs_version\\node_modules\\a-big-triangle\\triangle.js","original":{"line":28,"column":0},"generated":{"line":28,"column":0}},{"source":"nodejs_version\\node_modules\\a-big-triangle\\triangle.js","original":{"line":29,"column":0},"generated":{"line":29,"column":0}},{"source":"nodejs_version\\node_modules\\a-big-triangle\\triangle.js","original":{"line":30,"column":0},"generated":{"line":30,"column":0}}],"sources":{"nodejs_version\\node_modules\\a-big-triangle\\triangle.js":"'use strict'\n\nvar weakMap      = typeof WeakMap === 'undefined' ? require('weak-map') : WeakMap\nvar createBuffer = require('gl-buffer')\nvar createVAO    = require('gl-vao')\n\nvar TriangleCache = new weakMap()\n\nfunction createABigTriangle(gl) {\n\n  var triangleVAO = TriangleCache.get(gl)\n  var handle = triangleVAO && (triangleVAO._triangleBuffer.handle || triangleVAO._triangleBuffer.buffer)\n  if(!handle || !gl.isBuffer(handle)) {\n    var buf = createBuffer(gl, new Float32Array([-1, -1, -1, 4, 4, -1]))\n    triangleVAO = createVAO(gl, [\n      { buffer: buf,\n        type: gl.FLOAT,\n        size: 2\n      }\n    ])\n    triangleVAO._triangleBuffer = buf\n    TriangleCache.set(gl, triangleVAO)\n  }\n  triangleVAO.bind()\n  gl.drawArrays(gl.TRIANGLES, 0, 3)\n  triangleVAO.unbind()\n}\n\nmodule.exports = createABigTriangle\n"},"lineCount":30}},"hash":"763c8e489f078f134c5c2f5a32e5e5a9","cacheData":{"env":{}}}