{"dependencies":[{"name":"C:\\Users\\qison\\package.json","includedInParent":true,"mtime":1526331035212},{"name":"C:\\Users\\qison\\Google Drive\\tfjs_vae\\nodejs_version\\node_modules\\plotly.js\\package.json","includedInParent":true,"mtime":499162500000},{"name":"../../components/colorscale/color_attributes","loc":{"line":11,"column":25}},{"name":"../../components/colorscale/attributes","loc":{"line":12,"column":30}},{"name":"../../components/colorbar/attributes","loc":{"line":13,"column":28}},{"name":"../mesh3d/attributes","loc":{"line":14,"column":26}},{"name":"../../plots/attributes","loc":{"line":15,"column":24}},{"name":"../../lib/extend","loc":{"line":17,"column":25}}],"generated":{"js":"/**\n* Copyright 2012-2018, Plotly, Inc.\n* All rights reserved.\n*\n* This source code is licensed under the MIT license found in the\n* LICENSE file in the root directory of this source tree.\n*/\n\n'use strict';\n\nvar colorAttrs = require('../../components/colorscale/color_attributes');\nvar colorscaleAttrs = require('../../components/colorscale/attributes');\nvar colorbarAttrs = require('../../components/colorbar/attributes');\nvar mesh3dAttrs = require('../mesh3d/attributes');\nvar baseAttrs = require('../../plots/attributes');\n\nvar extendFlat = require('../../lib/extend').extendFlat;\n\nvar attrs = {\n    x: {\n        valType: 'data_array',\n        role: 'info',\n        editType: 'calc+clearAxisTypes',\n        description: [\n            'Sets the x coordinates of the vector field',\n            'and of the displayed cones.'\n        ].join(' ')\n    },\n    y: {\n        valType: 'data_array',\n        role: 'info',\n        editType: 'calc+clearAxisTypes',\n        description: [\n            'Sets the y coordinates of the vector field',\n            'and of the displayed cones.'\n        ].join(' ')\n    },\n    z: {\n        valType: 'data_array',\n        role: 'info',\n        editType: 'calc+clearAxisTypes',\n        description: [\n            'Sets the z coordinates of the vector field',\n            'and of the displayed cones.'\n        ].join(' ')\n    },\n\n    u: {\n        valType: 'data_array',\n        editType: 'calc',\n        description: 'Sets the x components of the vector field.'\n    },\n    v: {\n        valType: 'data_array',\n        editType: 'calc',\n        description: 'Sets the y components of the vector field.'\n    },\n    w: {\n        valType: 'data_array',\n        editType: 'calc',\n        description: 'Sets the z components of the vector field.'\n    },\n\n    // TODO add way to specify cone positions independently of the vector field\n    // provided, similar to MATLAB's coneplot Cx/Cy/Cz meshgrids,\n    // see https://www.mathworks.com/help/matlab/ref/coneplot.html\n    //\n    // Alternatively, if our goal is only to 'fill in gaps' in the vector data,\n    // we could try to extend the heatmap 'connectgaps' algorithm to 3D.\n    // From AJ: this particular algorithm which amounts to a Poisson equation,\n    // both for interpolation and extrapolation - is the right one to use for\n    // cones too.  It makes a field with zero divergence, which is a good\n    // baseline assumption for vector fields.\n    //\n    // cones: {\n    //     // potential attributes to add:\n    //     //\n    //     // - meshmode: 'cartesian-product', 'pts', 'grid'\n    //     //\n    //     // under `meshmode: 'grid'`\n    //     // - (x|y|z)grid.start\n    //     // - (x|y|z)grid.end\n    //     // - (x|y|z)grid.size\n    //\n    //     x: {\n    //         valType: 'data_array',\n    //         editType: 'calc',\n    //         description: 'Sets the x coordinates of the cones to be displayed.'\n    //     },\n    //     y: {\n    //         valType: 'data_array',\n    //         editType: 'calc',\n    //         description: 'Sets the y coordinates of the cones to be displayed.'\n    //     },\n    //     z: {\n    //         valType: 'data_array',\n    //         editType: 'calc',\n    //         description: 'Sets the z coordinates of the cones to be displayed.'\n    //     },\n    //\n    //     editType: 'calc',\n    //     description: [\n    //         'By setting `cones.x`, `cones.y` and `cones.z` to 1D arrays,',\n    //         'plotly creates a mesh using the cartesian product of those 3 arrays.'\n    //     ].join(' ')\n    // },\n\n    sizemode: {\n        valType: 'enumerated',\n        values: ['scaled', 'absolute'],\n        role: 'info',\n        editType: 'calc',\n        dflt: 'scaled',\n        description: [\n            'Sets the mode by which the cones are sized.',\n            'If *scaled*, `sizeref` scales such that the reference cone size',\n            'for the maximum vector magnitude is 1.',\n            'If *absolute*, `sizeref` scales such that the reference cone size',\n            'for vector magnitude 1 is one grid unit.'\n        ].join(' ')\n    },\n    sizeref: {\n        valType: 'number',\n        role: 'info',\n        editType: 'calc',\n        min: 0,\n        dflt: 1,\n        description: 'Sets the cone size reference value.'\n    },\n\n    anchor: {\n        valType: 'enumerated',\n        role: 'info',\n        editType: 'calc',\n        values: ['tip', 'tail', 'cm', 'center'],\n        dflt: 'cm',\n        description: [\n            'Sets the cones\\' anchor with respect to their x/y/z positions.',\n            'Note that *cm* denote the cone\\'s center of mass which corresponds to',\n            '1/4 from the tail to tip.'\n        ].join(' ')\n    },\n\n    text: {\n        valType: 'string',\n        role: 'info',\n        dflt: '',\n        arrayOk: true,\n        editType: 'calc',\n        description: [\n            'Sets the text elements associated with the cones.',\n            'If trace `hoverinfo` contains a *text* flag and *hovertext* is not set,',\n            'these elements will be seen in the hover labels.'\n        ].join(' ')\n    }\n};\n\nextendFlat(attrs, colorAttrs('', 'calc', true), {\n    showscale: colorscaleAttrs.showscale,\n    colorbar: colorbarAttrs\n});\ndelete attrs.color;\n\nvar fromMesh3d = ['opacity', 'lightposition', 'lighting'];\n\nfromMesh3d.forEach(function(k) {\n    attrs[k] = mesh3dAttrs[k];\n});\n\nattrs.hoverinfo = extendFlat({}, baseAttrs.hoverinfo, {\n    editType: 'calc',\n    flags: ['x', 'y', 'z', 'u', 'v', 'w', 'norm', 'text', 'name'],\n    dflt: 'x+y+z+norm+text+name'\n});\n\nmodule.exports = attrs;\n","map":{"mappings":[{"source":"nodejs_version\\node_modules\\plotly.js\\src\\traces\\cone\\attributes.js","original":{"line":1,"column":0},"generated":{"line":1,"column":0}},{"source":"nodejs_version\\node_modules\\plotly.js\\src\\traces\\cone\\attributes.js","original":{"line":2,"column":0},"generated":{"line":2,"column":0}},{"source":"nodejs_version\\node_modules\\plotly.js\\src\\traces\\cone\\attributes.js","original":{"line":3,"column":0},"generated":{"line":3,"column":0}},{"source":"nodejs_version\\node_modules\\plotly.js\\src\\traces\\cone\\attributes.js","original":{"line":4,"column":0},"generated":{"line":4,"column":0}},{"source":"nodejs_version\\node_modules\\plotly.js\\src\\traces\\cone\\attributes.js","original":{"line":5,"column":0},"generated":{"line":5,"column":0}},{"source":"nodejs_version\\node_modules\\plotly.js\\src\\traces\\cone\\attributes.js","original":{"line":6,"column":0},"generated":{"line":6,"column":0}},{"source":"nodejs_version\\node_modules\\plotly.js\\src\\traces\\cone\\attributes.js","original":{"line":7,"column":0},"generated":{"line":7,"column":0}},{"source":"nodejs_version\\node_modules\\plotly.js\\src\\traces\\cone\\attributes.js","original":{"line":8,"column":0},"generated":{"line":8,"column":0}},{"source":"nodejs_version\\node_modules\\plotly.js\\src\\traces\\cone\\attributes.js","original":{"line":9,"column":0},"generated":{"line":9,"column":0}},{"source":"nodejs_version\\node_modules\\plotly.js\\src\\traces\\cone\\attributes.js","original":{"line":10,"column":0},"generated":{"line":10,"column":0}},{"source":"nodejs_version\\node_modules\\plotly.js\\src\\traces\\cone\\attributes.js","original":{"line":11,"column":0},"generated":{"line":11,"column":0}},{"source":"nodejs_version\\node_modules\\plotly.js\\src\\traces\\cone\\attributes.js","original":{"line":12,"column":0},"generated":{"line":12,"column":0}},{"source":"nodejs_version\\node_modules\\plotly.js\\src\\traces\\cone\\attributes.js","original":{"line":13,"column":0},"generated":{"line":13,"column":0}},{"source":"nodejs_version\\node_modules\\plotly.js\\src\\traces\\cone\\attributes.js","original":{"line":14,"column":0},"generated":{"line":14,"column":0}},{"source":"nodejs_version\\node_modules\\plotly.js\\src\\traces\\cone\\attributes.js","original":{"line":15,"column":0},"generated":{"line":15,"column":0}},{"source":"nodejs_version\\node_modules\\plotly.js\\src\\traces\\cone\\attributes.js","original":{"line":16,"column":0},"generated":{"line":16,"column":0}},{"source":"nodejs_version\\node_modules\\plotly.js\\src\\traces\\cone\\attributes.js","original":{"line":17,"column":0},"generated":{"line":17,"column":0}},{"source":"nodejs_version\\node_modules\\plotly.js\\src\\traces\\cone\\attributes.js","original":{"line":18,"column":0},"generated":{"line":18,"column":0}},{"source":"nodejs_version\\node_modules\\plotly.js\\src\\traces\\cone\\attributes.js","original":{"line":19,"column":0},"generated":{"line":19,"column":0}},{"source":"nodejs_version\\node_modules\\plotly.js\\src\\traces\\cone\\attributes.js","original":{"line":20,"column":0},"generated":{"line":20,"column":0}},{"source":"nodejs_version\\node_modules\\plotly.js\\src\\traces\\cone\\attributes.js","original":{"line":21,"column":0},"generated":{"line":21,"column":0}},{"source":"nodejs_version\\node_modules\\plotly.js\\src\\traces\\cone\\attributes.js","original":{"line":22,"column":0},"generated":{"line":22,"column":0}},{"source":"nodejs_version\\node_modules\\plotly.js\\src\\traces\\cone\\attributes.js","original":{"line":23,"column":0},"generated":{"line":23,"column":0}},{"source":"nodejs_version\\node_modules\\plotly.js\\src\\traces\\cone\\attributes.js","original":{"line":24,"column":0},"generated":{"line":24,"column":0}},{"source":"nodejs_version\\node_modules\\plotly.js\\src\\traces\\cone\\attributes.js","original":{"line":25,"column":0},"generated":{"line":25,"column":0}},{"source":"nodejs_version\\node_modules\\plotly.js\\src\\traces\\cone\\attributes.js","original":{"line":26,"column":0},"generated":{"line":26,"column":0}},{"source":"nodejs_version\\node_modules\\plotly.js\\src\\traces\\cone\\attributes.js","original":{"line":27,"column":0},"generated":{"line":27,"column":0}},{"source":"nodejs_version\\node_modules\\plotly.js\\src\\traces\\cone\\attributes.js","original":{"line":28,"column":0},"generated":{"line":28,"column":0}},{"source":"nodejs_version\\node_modules\\plotly.js\\src\\traces\\cone\\attributes.js","original":{"line":29,"column":0},"generated":{"line":29,"column":0}},{"source":"nodejs_version\\node_modules\\plotly.js\\src\\traces\\cone\\attributes.js","original":{"line":30,"column":0},"generated":{"line":30,"column":0}},{"source":"nodejs_version\\node_modules\\plotly.js\\src\\traces\\cone\\attributes.js","original":{"line":31,"column":0},"generated":{"line":31,"column":0}},{"source":"nodejs_version\\node_modules\\plotly.js\\src\\traces\\cone\\attributes.js","original":{"line":32,"column":0},"generated":{"line":32,"column":0}},{"source":"nodejs_version\\node_modules\\plotly.js\\src\\traces\\cone\\attributes.js","original":{"line":33,"column":0},"generated":{"line":33,"column":0}},{"source":"nodejs_version\\node_modules\\plotly.js\\src\\traces\\cone\\attributes.js","original":{"line":34,"column":0},"generated":{"line":34,"column":0}},{"source":"nodejs_version\\node_modules\\plotly.js\\src\\traces\\cone\\attributes.js","original":{"line":35,"column":0},"generated":{"line":35,"column":0}},{"source":"nodejs_version\\node_modules\\plotly.js\\src\\traces\\cone\\attributes.js","original":{"line":36,"column":0},"generated":{"line":36,"column":0}},{"source":"nodejs_version\\node_modules\\plotly.js\\src\\traces\\cone\\attributes.js","original":{"line":37,"column":0},"generated":{"line":37,"column":0}},{"source":"nodejs_version\\node_modules\\plotly.js\\src\\traces\\cone\\attributes.js","original":{"line":38,"column":0},"generated":{"line":38,"column":0}},{"source":"nodejs_version\\node_modules\\plotly.js\\src\\traces\\cone\\attributes.js","original":{"line":39,"column":0},"generated":{"line":39,"column":0}},{"source":"nodejs_version\\node_modules\\plotly.js\\src\\traces\\cone\\attributes.js","original":{"line":40,"column":0},"generated":{"line":40,"column":0}},{"source":"nodejs_version\\node_modules\\plotly.js\\src\\traces\\cone\\attributes.js","original":{"line":41,"column":0},"generated":{"line":41,"column":0}},{"source":"nodejs_version\\node_modules\\plotly.js\\src\\traces\\cone\\attributes.js","original":{"line":42,"column":0},"generated":{"line":42,"column":0}},{"source":"nodejs_version\\node_modules\\plotly.js\\src\\traces\\cone\\attributes.js","original":{"line":43,"column":0},"generated":{"line":43,"column":0}},{"source":"nodejs_version\\node_modules\\plotly.js\\src\\traces\\cone\\attributes.js","original":{"line":44,"column":0},"generated":{"line":44,"column":0}},{"source":"nodejs_version\\node_modules\\plotly.js\\src\\traces\\cone\\attributes.js","original":{"line":45,"column":0},"generated":{"line":45,"column":0}},{"source":"nodejs_version\\node_modules\\plotly.js\\src\\traces\\cone\\attributes.js","original":{"line":46,"column":0},"generated":{"line":46,"column":0}},{"source":"nodejs_version\\node_modules\\plotly.js\\src\\traces\\cone\\attributes.js","original":{"line":47,"column":0},"generated":{"line":47,"column":0}},{"source":"nodejs_version\\node_modules\\plotly.js\\src\\traces\\cone\\attributes.js","original":{"line":48,"column":0},"generated":{"line":48,"column":0}},{"source":"nodejs_version\\node_modules\\plotly.js\\src\\traces\\cone\\attributes.js","original":{"line":49,"column":0},"generated":{"line":49,"column":0}},{"source":"nodejs_version\\node_modules\\plotly.js\\src\\traces\\cone\\attributes.js","original":{"line":50,"column":0},"generated":{"line":50,"column":0}},{"source":"nodejs_version\\node_modules\\plotly.js\\src\\traces\\cone\\attributes.js","original":{"line":51,"column":0},"generated":{"line":51,"column":0}},{"source":"nodejs_version\\node_modules\\plotly.js\\src\\traces\\cone\\attributes.js","original":{"line":52,"column":0},"generated":{"line":52,"column":0}},{"source":"nodejs_version\\node_modules\\plotly.js\\src\\traces\\cone\\attributes.js","original":{"line":53,"column":0},"generated":{"line":53,"column":0}},{"source":"nodejs_version\\node_modules\\plotly.js\\src\\traces\\cone\\attributes.js","original":{"line":54,"column":0},"generated":{"line":54,"column":0}},{"source":"nodejs_version\\node_modules\\plotly.js\\src\\traces\\cone\\attributes.js","original":{"line":55,"column":0},"generated":{"line":55,"column":0}},{"source":"nodejs_version\\node_modules\\plotly.js\\src\\traces\\cone\\attributes.js","original":{"line":56,"column":0},"generated":{"line":56,"column":0}},{"source":"nodejs_version\\node_modules\\plotly.js\\src\\traces\\cone\\attributes.js","original":{"line":57,"column":0},"generated":{"line":57,"column":0}},{"source":"nodejs_version\\node_modules\\plotly.js\\src\\traces\\cone\\attributes.js","original":{"line":58,"column":0},"generated":{"line":58,"column":0}},{"source":"nodejs_version\\node_modules\\plotly.js\\src\\traces\\cone\\attributes.js","original":{"line":59,"column":0},"generated":{"line":59,"column":0}},{"source":"nodejs_version\\node_modules\\plotly.js\\src\\traces\\cone\\attributes.js","original":{"line":60,"column":0},"generated":{"line":60,"column":0}},{"source":"nodejs_version\\node_modules\\plotly.js\\src\\traces\\cone\\attributes.js","original":{"line":61,"column":0},"generated":{"line":61,"column":0}},{"source":"nodejs_version\\node_modules\\plotly.js\\src\\traces\\cone\\attributes.js","original":{"line":62,"column":0},"generated":{"line":62,"column":0}},{"source":"nodejs_version\\node_modules\\plotly.js\\src\\traces\\cone\\attributes.js","original":{"line":63,"column":0},"generated":{"line":63,"column":0}},{"source":"nodejs_version\\node_modules\\plotly.js\\src\\traces\\cone\\attributes.js","original":{"line":64,"column":0},"generated":{"line":64,"column":0}},{"source":"nodejs_version\\node_modules\\plotly.js\\src\\traces\\cone\\attributes.js","original":{"line":65,"column":0},"generated":{"line":65,"column":0}},{"source":"nodejs_version\\node_modules\\plotly.js\\src\\traces\\cone\\attributes.js","original":{"line":66,"column":0},"generated":{"line":66,"column":0}},{"source":"nodejs_version\\node_modules\\plotly.js\\src\\traces\\cone\\attributes.js","original":{"line":67,"column":0},"generated":{"line":67,"column":0}},{"source":"nodejs_version\\node_modules\\plotly.js\\src\\traces\\cone\\attributes.js","original":{"line":68,"column":0},"generated":{"line":68,"column":0}},{"source":"nodejs_version\\node_modules\\plotly.js\\src\\traces\\cone\\attributes.js","original":{"line":69,"column":0},"generated":{"line":69,"column":0}},{"source":"nodejs_version\\node_modules\\plotly.js\\src\\traces\\cone\\attributes.js","original":{"line":70,"column":0},"generated":{"line":70,"column":0}},{"source":"nodejs_version\\node_modules\\plotly.js\\src\\traces\\cone\\attributes.js","original":{"line":71,"column":0},"generated":{"line":71,"column":0}},{"source":"nodejs_version\\node_modules\\plotly.js\\src\\traces\\cone\\attributes.js","original":{"line":72,"column":0},"generated":{"line":72,"column":0}},{"source":"nodejs_version\\node_modules\\plotly.js\\src\\traces\\cone\\attributes.js","original":{"line":73,"column":0},"generated":{"line":73,"column":0}},{"source":"nodejs_version\\node_modules\\plotly.js\\src\\traces\\cone\\attributes.js","original":{"line":74,"column":0},"generated":{"line":74,"column":0}},{"source":"nodejs_version\\node_modules\\plotly.js\\src\\traces\\cone\\attributes.js","original":{"line":75,"column":0},"generated":{"line":75,"column":0}},{"source":"nodejs_version\\node_modules\\plotly.js\\src\\traces\\cone\\attributes.js","original":{"line":76,"column":0},"generated":{"line":76,"column":0}},{"source":"nodejs_version\\node_modules\\plotly.js\\src\\traces\\cone\\attributes.js","original":{"line":77,"column":0},"generated":{"line":77,"column":0}},{"source":"nodejs_version\\node_modules\\plotly.js\\src\\traces\\cone\\attributes.js","original":{"line":78,"column":0},"generated":{"line":78,"column":0}},{"source":"nodejs_version\\node_modules\\plotly.js\\src\\traces\\cone\\attributes.js","original":{"line":79,"column":0},"generated":{"line":79,"column":0}},{"source":"nodejs_version\\node_modules\\plotly.js\\src\\traces\\cone\\attributes.js","original":{"line":80,"column":0},"generated":{"line":80,"column":0}},{"source":"nodejs_version\\node_modules\\plotly.js\\src\\traces\\cone\\attributes.js","original":{"line":81,"column":0},"generated":{"line":81,"column":0}},{"source":"nodejs_version\\node_modules\\plotly.js\\src\\traces\\cone\\attributes.js","original":{"line":82,"column":0},"generated":{"line":82,"column":0}},{"source":"nodejs_version\\node_modules\\plotly.js\\src\\traces\\cone\\attributes.js","original":{"line":83,"column":0},"generated":{"line":83,"column":0}},{"source":"nodejs_version\\node_modules\\plotly.js\\src\\traces\\cone\\attributes.js","original":{"line":84,"column":0},"generated":{"line":84,"column":0}},{"source":"nodejs_version\\node_modules\\plotly.js\\src\\traces\\cone\\attributes.js","original":{"line":85,"column":0},"generated":{"line":85,"column":0}},{"source":"nodejs_version\\node_modules\\plotly.js\\src\\traces\\cone\\attributes.js","original":{"line":86,"column":0},"generated":{"line":86,"column":0}},{"source":"nodejs_version\\node_modules\\plotly.js\\src\\traces\\cone\\attributes.js","original":{"line":87,"column":0},"generated":{"line":87,"column":0}},{"source":"nodejs_version\\node_modules\\plotly.js\\src\\traces\\cone\\attributes.js","original":{"line":88,"column":0},"generated":{"line":88,"column":0}},{"source":"nodejs_version\\node_modules\\plotly.js\\src\\traces\\cone\\attributes.js","original":{"line":89,"column":0},"generated":{"line":89,"column":0}},{"source":"nodejs_version\\node_modules\\plotly.js\\src\\traces\\cone\\attributes.js","original":{"line":90,"column":0},"generated":{"line":90,"column":0}},{"source":"nodejs_version\\node_modules\\plotly.js\\src\\traces\\cone\\attributes.js","original":{"line":91,"column":0},"generated":{"line":91,"column":0}},{"source":"nodejs_version\\node_modules\\plotly.js\\src\\traces\\cone\\attributes.js","original":{"line":92,"column":0},"generated":{"line":92,"column":0}},{"source":"nodejs_version\\node_modules\\plotly.js\\src\\traces\\cone\\attributes.js","original":{"line":93,"column":0},"generated":{"line":93,"column":0}},{"source":"nodejs_version\\node_modules\\plotly.js\\src\\traces\\cone\\attributes.js","original":{"line":94,"column":0},"generated":{"line":94,"column":0}},{"source":"nodejs_version\\node_modules\\plotly.js\\src\\traces\\cone\\attributes.js","original":{"line":95,"column":0},"generated":{"line":95,"column":0}},{"source":"nodejs_version\\node_modules\\plotly.js\\src\\traces\\cone\\attributes.js","original":{"line":96,"column":0},"generated":{"line":96,"column":0}},{"source":"nodejs_version\\node_modules\\plotly.js\\src\\traces\\cone\\attributes.js","original":{"line":97,"column":0},"generated":{"line":97,"column":0}},{"source":"nodejs_version\\node_modules\\plotly.js\\src\\traces\\cone\\attributes.js","original":{"line":98,"column":0},"generated":{"line":98,"column":0}},{"source":"nodejs_version\\node_modules\\plotly.js\\src\\traces\\cone\\attributes.js","original":{"line":99,"column":0},"generated":{"line":99,"column":0}},{"source":"nodejs_version\\node_modules\\plotly.js\\src\\traces\\cone\\attributes.js","original":{"line":100,"column":0},"generated":{"line":100,"column":0}},{"source":"nodejs_version\\node_modules\\plotly.js\\src\\traces\\cone\\attributes.js","original":{"line":101,"column":0},"generated":{"line":101,"column":0}},{"source":"nodejs_version\\node_modules\\plotly.js\\src\\traces\\cone\\attributes.js","original":{"line":102,"column":0},"generated":{"line":102,"column":0}},{"source":"nodejs_version\\node_modules\\plotly.js\\src\\traces\\cone\\attributes.js","original":{"line":103,"column":0},"generated":{"line":103,"column":0}},{"source":"nodejs_version\\node_modules\\plotly.js\\src\\traces\\cone\\attributes.js","original":{"line":104,"column":0},"generated":{"line":104,"column":0}},{"source":"nodejs_version\\node_modules\\plotly.js\\src\\traces\\cone\\attributes.js","original":{"line":105,"column":0},"generated":{"line":105,"column":0}},{"source":"nodejs_version\\node_modules\\plotly.js\\src\\traces\\cone\\attributes.js","original":{"line":106,"column":0},"generated":{"line":106,"column":0}},{"source":"nodejs_version\\node_modules\\plotly.js\\src\\traces\\cone\\attributes.js","original":{"line":107,"column":0},"generated":{"line":107,"column":0}},{"source":"nodejs_version\\node_modules\\plotly.js\\src\\traces\\cone\\attributes.js","original":{"line":108,"column":0},"generated":{"line":108,"column":0}},{"source":"nodejs_version\\node_modules\\plotly.js\\src\\traces\\cone\\attributes.js","original":{"line":109,"column":0},"generated":{"line":109,"column":0}},{"source":"nodejs_version\\node_modules\\plotly.js\\src\\traces\\cone\\attributes.js","original":{"line":110,"column":0},"generated":{"line":110,"column":0}},{"source":"nodejs_version\\node_modules\\plotly.js\\src\\traces\\cone\\attributes.js","original":{"line":111,"column":0},"generated":{"line":111,"column":0}},{"source":"nodejs_version\\node_modules\\plotly.js\\src\\traces\\cone\\attributes.js","original":{"line":112,"column":0},"generated":{"line":112,"column":0}},{"source":"nodejs_version\\node_modules\\plotly.js\\src\\traces\\cone\\attributes.js","original":{"line":113,"column":0},"generated":{"line":113,"column":0}},{"source":"nodejs_version\\node_modules\\plotly.js\\src\\traces\\cone\\attributes.js","original":{"line":114,"column":0},"generated":{"line":114,"column":0}},{"source":"nodejs_version\\node_modules\\plotly.js\\src\\traces\\cone\\attributes.js","original":{"line":115,"column":0},"generated":{"line":115,"column":0}},{"source":"nodejs_version\\node_modules\\plotly.js\\src\\traces\\cone\\attributes.js","original":{"line":116,"column":0},"generated":{"line":116,"column":0}},{"source":"nodejs_version\\node_modules\\plotly.js\\src\\traces\\cone\\attributes.js","original":{"line":117,"column":0},"generated":{"line":117,"column":0}},{"source":"nodejs_version\\node_modules\\plotly.js\\src\\traces\\cone\\attributes.js","original":{"line":118,"column":0},"generated":{"line":118,"column":0}},{"source":"nodejs_version\\node_modules\\plotly.js\\src\\traces\\cone\\attributes.js","original":{"line":119,"column":0},"generated":{"line":119,"column":0}},{"source":"nodejs_version\\node_modules\\plotly.js\\src\\traces\\cone\\attributes.js","original":{"line":120,"column":0},"generated":{"line":120,"column":0}},{"source":"nodejs_version\\node_modules\\plotly.js\\src\\traces\\cone\\attributes.js","original":{"line":121,"column":0},"generated":{"line":121,"column":0}},{"source":"nodejs_version\\node_modules\\plotly.js\\src\\traces\\cone\\attributes.js","original":{"line":122,"column":0},"generated":{"line":122,"column":0}},{"source":"nodejs_version\\node_modules\\plotly.js\\src\\traces\\cone\\attributes.js","original":{"line":123,"column":0},"generated":{"line":123,"column":0}},{"source":"nodejs_version\\node_modules\\plotly.js\\src\\traces\\cone\\attributes.js","original":{"line":124,"column":0},"generated":{"line":124,"column":0}},{"source":"nodejs_version\\node_modules\\plotly.js\\src\\traces\\cone\\attributes.js","original":{"line":125,"column":0},"generated":{"line":125,"column":0}},{"source":"nodejs_version\\node_modules\\plotly.js\\src\\traces\\cone\\attributes.js","original":{"line":126,"column":0},"generated":{"line":126,"column":0}},{"source":"nodejs_version\\node_modules\\plotly.js\\src\\traces\\cone\\attributes.js","original":{"line":127,"column":0},"generated":{"line":127,"column":0}},{"source":"nodejs_version\\node_modules\\plotly.js\\src\\traces\\cone\\attributes.js","original":{"line":128,"column":0},"generated":{"line":128,"column":0}},{"source":"nodejs_version\\node_modules\\plotly.js\\src\\traces\\cone\\attributes.js","original":{"line":129,"column":0},"generated":{"line":129,"column":0}},{"source":"nodejs_version\\node_modules\\plotly.js\\src\\traces\\cone\\attributes.js","original":{"line":130,"column":0},"generated":{"line":130,"column":0}},{"source":"nodejs_version\\node_modules\\plotly.js\\src\\traces\\cone\\attributes.js","original":{"line":131,"column":0},"generated":{"line":131,"column":0}},{"source":"nodejs_version\\node_modules\\plotly.js\\src\\traces\\cone\\attributes.js","original":{"line":132,"column":0},"generated":{"line":132,"column":0}},{"source":"nodejs_version\\node_modules\\plotly.js\\src\\traces\\cone\\attributes.js","original":{"line":133,"column":0},"generated":{"line":133,"column":0}},{"source":"nodejs_version\\node_modules\\plotly.js\\src\\traces\\cone\\attributes.js","original":{"line":134,"column":0},"generated":{"line":134,"column":0}},{"source":"nodejs_version\\node_modules\\plotly.js\\src\\traces\\cone\\attributes.js","original":{"line":135,"column":0},"generated":{"line":135,"column":0}},{"source":"nodejs_version\\node_modules\\plotly.js\\src\\traces\\cone\\attributes.js","original":{"line":136,"column":0},"generated":{"line":136,"column":0}},{"source":"nodejs_version\\node_modules\\plotly.js\\src\\traces\\cone\\attributes.js","original":{"line":137,"column":0},"generated":{"line":137,"column":0}},{"source":"nodejs_version\\node_modules\\plotly.js\\src\\traces\\cone\\attributes.js","original":{"line":138,"column":0},"generated":{"line":138,"column":0}},{"source":"nodejs_version\\node_modules\\plotly.js\\src\\traces\\cone\\attributes.js","original":{"line":139,"column":0},"generated":{"line":139,"column":0}},{"source":"nodejs_version\\node_modules\\plotly.js\\src\\traces\\cone\\attributes.js","original":{"line":140,"column":0},"generated":{"line":140,"column":0}},{"source":"nodejs_version\\node_modules\\plotly.js\\src\\traces\\cone\\attributes.js","original":{"line":141,"column":0},"generated":{"line":141,"column":0}},{"source":"nodejs_version\\node_modules\\plotly.js\\src\\traces\\cone\\attributes.js","original":{"line":142,"column":0},"generated":{"line":142,"column":0}},{"source":"nodejs_version\\node_modules\\plotly.js\\src\\traces\\cone\\attributes.js","original":{"line":143,"column":0},"generated":{"line":143,"column":0}},{"source":"nodejs_version\\node_modules\\plotly.js\\src\\traces\\cone\\attributes.js","original":{"line":144,"column":0},"generated":{"line":144,"column":0}},{"source":"nodejs_version\\node_modules\\plotly.js\\src\\traces\\cone\\attributes.js","original":{"line":145,"column":0},"generated":{"line":145,"column":0}},{"source":"nodejs_version\\node_modules\\plotly.js\\src\\traces\\cone\\attributes.js","original":{"line":146,"column":0},"generated":{"line":146,"column":0}},{"source":"nodejs_version\\node_modules\\plotly.js\\src\\traces\\cone\\attributes.js","original":{"line":147,"column":0},"generated":{"line":147,"column":0}},{"source":"nodejs_version\\node_modules\\plotly.js\\src\\traces\\cone\\attributes.js","original":{"line":148,"column":0},"generated":{"line":148,"column":0}},{"source":"nodejs_version\\node_modules\\plotly.js\\src\\traces\\cone\\attributes.js","original":{"line":149,"column":0},"generated":{"line":149,"column":0}},{"source":"nodejs_version\\node_modules\\plotly.js\\src\\traces\\cone\\attributes.js","original":{"line":150,"column":0},"generated":{"line":150,"column":0}},{"source":"nodejs_version\\node_modules\\plotly.js\\src\\traces\\cone\\attributes.js","original":{"line":151,"column":0},"generated":{"line":151,"column":0}},{"source":"nodejs_version\\node_modules\\plotly.js\\src\\traces\\cone\\attributes.js","original":{"line":152,"column":0},"generated":{"line":152,"column":0}},{"source":"nodejs_version\\node_modules\\plotly.js\\src\\traces\\cone\\attributes.js","original":{"line":153,"column":0},"generated":{"line":153,"column":0}},{"source":"nodejs_version\\node_modules\\plotly.js\\src\\traces\\cone\\attributes.js","original":{"line":154,"column":0},"generated":{"line":154,"column":0}},{"source":"nodejs_version\\node_modules\\plotly.js\\src\\traces\\cone\\attributes.js","original":{"line":155,"column":0},"generated":{"line":155,"column":0}},{"source":"nodejs_version\\node_modules\\plotly.js\\src\\traces\\cone\\attributes.js","original":{"line":156,"column":0},"generated":{"line":156,"column":0}},{"source":"nodejs_version\\node_modules\\plotly.js\\src\\traces\\cone\\attributes.js","original":{"line":157,"column":0},"generated":{"line":157,"column":0}},{"source":"nodejs_version\\node_modules\\plotly.js\\src\\traces\\cone\\attributes.js","original":{"line":158,"column":0},"generated":{"line":158,"column":0}},{"source":"nodejs_version\\node_modules\\plotly.js\\src\\traces\\cone\\attributes.js","original":{"line":159,"column":0},"generated":{"line":159,"column":0}},{"source":"nodejs_version\\node_modules\\plotly.js\\src\\traces\\cone\\attributes.js","original":{"line":160,"column":0},"generated":{"line":160,"column":0}},{"source":"nodejs_version\\node_modules\\plotly.js\\src\\traces\\cone\\attributes.js","original":{"line":161,"column":0},"generated":{"line":161,"column":0}},{"source":"nodejs_version\\node_modules\\plotly.js\\src\\traces\\cone\\attributes.js","original":{"line":162,"column":0},"generated":{"line":162,"column":0}},{"source":"nodejs_version\\node_modules\\plotly.js\\src\\traces\\cone\\attributes.js","original":{"line":163,"column":0},"generated":{"line":163,"column":0}},{"source":"nodejs_version\\node_modules\\plotly.js\\src\\traces\\cone\\attributes.js","original":{"line":164,"column":0},"generated":{"line":164,"column":0}},{"source":"nodejs_version\\node_modules\\plotly.js\\src\\traces\\cone\\attributes.js","original":{"line":165,"column":0},"generated":{"line":165,"column":0}},{"source":"nodejs_version\\node_modules\\plotly.js\\src\\traces\\cone\\attributes.js","original":{"line":166,"column":0},"generated":{"line":166,"column":0}},{"source":"nodejs_version\\node_modules\\plotly.js\\src\\traces\\cone\\attributes.js","original":{"line":167,"column":0},"generated":{"line":167,"column":0}},{"source":"nodejs_version\\node_modules\\plotly.js\\src\\traces\\cone\\attributes.js","original":{"line":168,"column":0},"generated":{"line":168,"column":0}},{"source":"nodejs_version\\node_modules\\plotly.js\\src\\traces\\cone\\attributes.js","original":{"line":169,"column":0},"generated":{"line":169,"column":0}},{"source":"nodejs_version\\node_modules\\plotly.js\\src\\traces\\cone\\attributes.js","original":{"line":170,"column":0},"generated":{"line":170,"column":0}},{"source":"nodejs_version\\node_modules\\plotly.js\\src\\traces\\cone\\attributes.js","original":{"line":171,"column":0},"generated":{"line":171,"column":0}},{"source":"nodejs_version\\node_modules\\plotly.js\\src\\traces\\cone\\attributes.js","original":{"line":172,"column":0},"generated":{"line":172,"column":0}},{"source":"nodejs_version\\node_modules\\plotly.js\\src\\traces\\cone\\attributes.js","original":{"line":173,"column":0},"generated":{"line":173,"column":0}},{"source":"nodejs_version\\node_modules\\plotly.js\\src\\traces\\cone\\attributes.js","original":{"line":174,"column":0},"generated":{"line":174,"column":0}},{"source":"nodejs_version\\node_modules\\plotly.js\\src\\traces\\cone\\attributes.js","original":{"line":175,"column":0},"generated":{"line":175,"column":0}},{"source":"nodejs_version\\node_modules\\plotly.js\\src\\traces\\cone\\attributes.js","original":{"line":176,"column":0},"generated":{"line":176,"column":0}},{"source":"nodejs_version\\node_modules\\plotly.js\\src\\traces\\cone\\attributes.js","original":{"line":177,"column":0},"generated":{"line":177,"column":0}}],"sources":{"nodejs_version\\node_modules\\plotly.js\\src\\traces\\cone\\attributes.js":"/**\n* Copyright 2012-2018, Plotly, Inc.\n* All rights reserved.\n*\n* This source code is licensed under the MIT license found in the\n* LICENSE file in the root directory of this source tree.\n*/\n\n'use strict';\n\nvar colorAttrs = require('../../components/colorscale/color_attributes');\nvar colorscaleAttrs = require('../../components/colorscale/attributes');\nvar colorbarAttrs = require('../../components/colorbar/attributes');\nvar mesh3dAttrs = require('../mesh3d/attributes');\nvar baseAttrs = require('../../plots/attributes');\n\nvar extendFlat = require('../../lib/extend').extendFlat;\n\nvar attrs = {\n    x: {\n        valType: 'data_array',\n        role: 'info',\n        editType: 'calc+clearAxisTypes',\n        description: [\n            'Sets the x coordinates of the vector field',\n            'and of the displayed cones.'\n        ].join(' ')\n    },\n    y: {\n        valType: 'data_array',\n        role: 'info',\n        editType: 'calc+clearAxisTypes',\n        description: [\n            'Sets the y coordinates of the vector field',\n            'and of the displayed cones.'\n        ].join(' ')\n    },\n    z: {\n        valType: 'data_array',\n        role: 'info',\n        editType: 'calc+clearAxisTypes',\n        description: [\n            'Sets the z coordinates of the vector field',\n            'and of the displayed cones.'\n        ].join(' ')\n    },\n\n    u: {\n        valType: 'data_array',\n        editType: 'calc',\n        description: 'Sets the x components of the vector field.'\n    },\n    v: {\n        valType: 'data_array',\n        editType: 'calc',\n        description: 'Sets the y components of the vector field.'\n    },\n    w: {\n        valType: 'data_array',\n        editType: 'calc',\n        description: 'Sets the z components of the vector field.'\n    },\n\n    // TODO add way to specify cone positions independently of the vector field\n    // provided, similar to MATLAB's coneplot Cx/Cy/Cz meshgrids,\n    // see https://www.mathworks.com/help/matlab/ref/coneplot.html\n    //\n    // Alternatively, if our goal is only to 'fill in gaps' in the vector data,\n    // we could try to extend the heatmap 'connectgaps' algorithm to 3D.\n    // From AJ: this particular algorithm which amounts to a Poisson equation,\n    // both for interpolation and extrapolation - is the right one to use for\n    // cones too.  It makes a field with zero divergence, which is a good\n    // baseline assumption for vector fields.\n    //\n    // cones: {\n    //     // potential attributes to add:\n    //     //\n    //     // - meshmode: 'cartesian-product', 'pts', 'grid'\n    //     //\n    //     // under `meshmode: 'grid'`\n    //     // - (x|y|z)grid.start\n    //     // - (x|y|z)grid.end\n    //     // - (x|y|z)grid.size\n    //\n    //     x: {\n    //         valType: 'data_array',\n    //         editType: 'calc',\n    //         description: 'Sets the x coordinates of the cones to be displayed.'\n    //     },\n    //     y: {\n    //         valType: 'data_array',\n    //         editType: 'calc',\n    //         description: 'Sets the y coordinates of the cones to be displayed.'\n    //     },\n    //     z: {\n    //         valType: 'data_array',\n    //         editType: 'calc',\n    //         description: 'Sets the z coordinates of the cones to be displayed.'\n    //     },\n    //\n    //     editType: 'calc',\n    //     description: [\n    //         'By setting `cones.x`, `cones.y` and `cones.z` to 1D arrays,',\n    //         'plotly creates a mesh using the cartesian product of those 3 arrays.'\n    //     ].join(' ')\n    // },\n\n    sizemode: {\n        valType: 'enumerated',\n        values: ['scaled', 'absolute'],\n        role: 'info',\n        editType: 'calc',\n        dflt: 'scaled',\n        description: [\n            'Sets the mode by which the cones are sized.',\n            'If *scaled*, `sizeref` scales such that the reference cone size',\n            'for the maximum vector magnitude is 1.',\n            'If *absolute*, `sizeref` scales such that the reference cone size',\n            'for vector magnitude 1 is one grid unit.'\n        ].join(' ')\n    },\n    sizeref: {\n        valType: 'number',\n        role: 'info',\n        editType: 'calc',\n        min: 0,\n        dflt: 1,\n        description: 'Sets the cone size reference value.'\n    },\n\n    anchor: {\n        valType: 'enumerated',\n        role: 'info',\n        editType: 'calc',\n        values: ['tip', 'tail', 'cm', 'center'],\n        dflt: 'cm',\n        description: [\n            'Sets the cones\\' anchor with respect to their x/y/z positions.',\n            'Note that *cm* denote the cone\\'s center of mass which corresponds to',\n            '1/4 from the tail to tip.'\n        ].join(' ')\n    },\n\n    text: {\n        valType: 'string',\n        role: 'info',\n        dflt: '',\n        arrayOk: true,\n        editType: 'calc',\n        description: [\n            'Sets the text elements associated with the cones.',\n            'If trace `hoverinfo` contains a *text* flag and *hovertext* is not set,',\n            'these elements will be seen in the hover labels.'\n        ].join(' ')\n    }\n};\n\nextendFlat(attrs, colorAttrs('', 'calc', true), {\n    showscale: colorscaleAttrs.showscale,\n    colorbar: colorbarAttrs\n});\ndelete attrs.color;\n\nvar fromMesh3d = ['opacity', 'lightposition', 'lighting'];\n\nfromMesh3d.forEach(function(k) {\n    attrs[k] = mesh3dAttrs[k];\n});\n\nattrs.hoverinfo = extendFlat({}, baseAttrs.hoverinfo, {\n    editType: 'calc',\n    flags: ['x', 'y', 'z', 'u', 'v', 'w', 'norm', 'text', 'name'],\n    dflt: 'x+y+z+norm+text+name'\n});\n\nmodule.exports = attrs;\n"},"lineCount":177}},"hash":"c176a7405b62c943c2fcd4cc95b48b16","cacheData":{"env":{}}}